lgtv/__init__.py
lgtv/__main__.py
lgtv/cli.py
lgtv/config.py
lgtv/discovery.py
lgtv/tv.py
lgtv/utils.py
lgtv/commands/__init__.py
lgtv/commands/apps.py
lgtv/commands/control.py
lgtv/commands/discover_features.py
lgtv/commands/info.py
lgtv/commands/input_cmd.py
lgtv/commands/media.py
lgtv/commands/power.py
lgtv/commands/volume.py
lgtv_cli-0.1.0.dist-info/licenses/LICENSE
lgtv_cli-0.1.0.dist-info/METADATA
lgtv_cli-0.1.0.dist-info/WHEEL
lgtv_cli-0.1.0.dist-info/entry_points.txt
lgtv_cli-0.1.0.dist-info/top_level.txt
lgtv_cli-0.1.0.dist-info/RECORD
