Metadata-Version: 2.4
Name: lgtv-cli
Version: 0.1.0
Summary: Command-line tool for controlling LG WebOS Smart TVs
Author: LG TV CLI Contributors
License: MIT
Project-URL: Homepage, https://github.com/01dnot/lgtvcli
Project-URL: Repository, https://github.com/01dnot/lgtvcli
Keywords: lg,webos,tv,smart-tv,remote,control,cli,home-automation,iot
Classifier: Development Status :: 3 - Alpha
Classifier: Intended Audience :: End Users/Desktop
Classifier: License :: OSI Approved :: MIT License
Classifier: Programming Language :: Python :: 3
Classifier: Programming Language :: Python :: 3.8
Classifier: Programming Language :: Python :: 3.9
Classifier: Programming Language :: Python :: 3.10
Classifier: Programming Language :: Python :: 3.11
Classifier: Programming Language :: Python :: 3.12
Requires-Python: >=3.8
License-File: LICENSE
Requires-Dist: pywebostv>=0.8.9
Requires-Dist: click>=8.0
Requires-Dist: zeroconf>=0.39
Requires-Dist: wakeonlan>=3.0
Provides-Extra: dev
Requires-Dist: pytest>=7.0; extra == "dev"
Requires-Dist: pytest-cov>=4.0; extra == "dev"
Requires-Dist: black>=23.0; extra == "dev"
Requires-Dist: flake8>=6.0; extra == "dev"
Dynamic: license-file
